{
  "$schema": "https://json-schema.org/draft/2020-12/schema",
  "title": "POGO Field Research",
  "type": "object",
  "properties": {
    "_meta": { "type": "object" },
    "tasks": {
      "type": "array",
      "items": {
        "type": "object",
        "properties": {
          "category": { "type": "string" },
          "task": { "type": "string", "minLength": 3 },
          "reward": { "type": "string" },
          "encounter": { "type": "string" },
          "shiny": { "type": ["boolean", "null"] },
          "notes": { "type": "string" },
          "source": { "type": "string" },
          "url": { "type": "string", "format": "uri" },
          "ts": { "type": "string", "pattern": "^\\d{4}-\\d{2}-\\d{2}T\\d{2}:\\d{2}:\\d{2}Z$" }
        },
        "required": ["task", "source"],
        "additionalProperties": true
      }
    }
  },
  "required": ["tasks"],
  "additionalProperties": true
}